create_llm_agent/__init__.py
create_llm_agent/cli.py
create_llm_agent-0.1.0.dist-info/licenses/LICENSE
create_llm_agent-0.1.0.dist-info/METADATA
create_llm_agent-0.1.0.dist-info/WHEEL
create_llm_agent-0.1.0.dist-info/entry_points.txt
create_llm_agent-0.1.0.dist-info/top_level.txt
create_llm_agent-0.1.0.dist-info/RECORD
