Metadata-Version: 2.4
Name: create-llm-agent
Version: 0.1.0
Summary: A CLI tool to scaffold your first AI llm-agent project.
Home-page: https://gist.github.com/JimSP/5920dd06f31913eb42657ede1ae85cff
Author: Alexandre Moraes de Souza Lima
Author-email: alexandre.msl@gmail.com
Classifier: Programming Language :: Python :: 3
Classifier: License :: OSI Approved :: MIT License
Classifier: Operating System :: OS Independent
Requires-Python: >=3.6
License-File: LICENSE
Dynamic: author
Dynamic: author-email
Dynamic: classifier
Dynamic: description
Dynamic: description-content-type
Dynamic: home-page
Dynamic: license-file
Dynamic: requires-python
Dynamic: summary
